geode/Geode.py
geode/__init__.py
geode/classes/__init__.py
geode/classes/beacon.py
geode/classes/id.py
geode/classes/operator.py
geode/classes/pool.py
geode/classes/portal.py
geode/classes/token.py
geode/classes/validator.py
geode/exceptions/__init__.py
geode/exceptions/main.py
geode/globals/__init__.py
geode/globals/beacon.py
geode/globals/constants.py
geode/globals/id.py
geode/globals/network.py
geode/globals/token.py
geode/globals/validator.py
geode/utils/__init__.py
geode/utils/abi.py
geode/utils/crypto.py
geode/utils/id.py
geode/utils/merkle.py
geode/utils/solidity.py
geode/utils/token.py
geode/utils/wrappers.py
geode/utils/bls/__init__.py
geode/utils/bls/main.py
geode/utils/bls/ssz.py
geode/utils/bls/validate.py
geode_finance-1.0.0.dist-info/LICENSE
geode_finance-1.0.0.dist-info/METADATA
geode_finance-1.0.0.dist-info/WHEEL
geode_finance-1.0.0.dist-info/top_level.txt
geode_finance-1.0.0.dist-info/RECORD
