Metadata-Version: 2.1
Name: geode-finance
Version: 1.0.0
Summary: Python SDK for contributing to Geode Finance Ecosystem
Home-page: https://www.geode.fi/
Author: Ice Bear
Author-email: icebear@geode.fi
License: MIT
Keywords: ethereum,geode,web3
Platform: UNKNOWN
Classifier: License :: OSI Approved :: MIT License
Classifier: Programming Language :: Python :: 3
Classifier: Programming Language :: Python :: 3 :: Only
Classifier: Programming Language :: Python :: Implementation :: CPython
Requires-Python: >=3.6
Requires-Dist: web3
Requires-Dist: py-ecc
Requires-Dist: ssz
